meshtastic_pygui/__init__.py
meshtastic_pygui/__main__.py
meshtastic_PyGUI-2.7.6.dist-info/LICENSE
meshtastic_PyGUI-2.7.6.dist-info/METADATA
meshtastic_PyGUI-2.7.6.dist-info/WHEEL
meshtastic_PyGUI-2.7.6.dist-info/entry_points.txt
meshtastic_PyGUI-2.7.6.dist-info/top_level.txt
meshtastic_PyGUI-2.7.6.dist-info/RECORD
