Metadata-Version: 2.1
Name: meshtastic-PyGUI
Version: 2.7.6
Summary: A pre-alpha python GUI for meshtastic
Home-page: https://github.com/ZebusJesus/Meshtastic-PyGUI
Author: Zebus Jeus
Author-email: ZebusJeus@pm.me
License: MIT
Platform: UNKNOWN
Classifier: License :: OSI Approved :: MIT License
Classifier: Programming Language :: Python :: 3
Classifier: Programming Language :: Python :: 3.7
Requires-Python: >=3.6
License-File: LICENSE
Requires-Dist: meshtastic (>=1.2.5)
Requires-Dist: PySimpleGUI (>=4.34.0)
Requires-Dist: requests (>=2.25.1)
Requires-Dist: esptool (>=3.0)
